{".class":"MypyFile","_fullname":"assistant.modules.calendar.calendar_config","future_import_flags":[],"is_partial_stub_package":false,"is_stub":false,"names":{".class":"SymbolTable","CALENDAR_ENABLED":{".class":"SymbolTableNode","kind":"Gdef","node":{".class":"Var","flags":["is_inferred","has_explicit_value"],"fullname":"assistant.modules.calendar.calendar_config.CALENDAR_ENABLED","name":"CALENDAR_ENABLED","type":"builtins.bool"}},"DB_PATH":{".class":"SymbolTableNode","kind":"Gdef","node":{".class":"Var","flags":["is_inferred","has_explicit_value"],"fullname":"assistant.modules.calendar.calendar_config.DB_PATH","name":"DB_PATH","type":"builtins.str"}},"GOOGLE_CALENDAR_ENABLED":{".class":"SymbolTableNode","kind":"Gdef","node":{".class":"Var","flags":["is_inferred","has_explicit_value"],"fullname":"assistant.modules.calendar.calendar_config.GOOGLE_CALENDAR_ENABLED","name":"GOOGLE_CALENDAR_ENABLED","type":"builtins.bool"}},"GOOGLE_CLIENT_ID":{".class":"SymbolTableNode","kind":"Gdef","node":{".class":"Var","flags":["is_inferred","has_explicit_value"],"fullname":"assistant.modules.calendar.calendar_config.GOOGLE_CLIENT_ID","name":"GOOGLE_CLIENT_ID","type":"builtins.str"}},"GOOGLE_CLIENT_SECRET":{".class":"SymbolTableNode","kind":"Gdef","node":{".class":"Var","flags":["is_inferred","has_explicit_value"],"fullname":"assistant.modules.calendar.calendar_config.GOOGLE_CLIENT_SECRET","name":"GOOGLE_CLIENT_SECRET","type":"builtins.str"}},"GOOGLE_REDIRECT_URI":{".class":"SymbolTableNode","kind":"Gdef","node":{".class":"Var","flags":["is_inferred","has_explicit_value"],"fullname":"assistant.modules.calendar.calendar_config.GOOGLE_REDIRECT_URI","name":"GOOGLE_REDIRECT_URI","type":"builtins.str"}},"Path":{".class":"SymbolTableNode","cross_ref":"pathlib.Path","kind":"Gdef"},"TOKEN_FILE":{".class":"SymbolTableNode","kind":"Gdef","node":{".class":"Var","flags":["is_inferred","has_explicit_value"],"fullname":"assistant.modules.calendar.calendar_config.TOKEN_FILE","name":"TOKEN_FILE","type":"pathlib.Path"}},"__annotations__":{".class":"SymbolTableNode","kind":"Gdef","node":{".class":"Var","flags":["is_ready"],"fullname":"assistant.modules.calendar.calendar_config.__annotations__","name":"__annotations__","type":{".class":"Instance","args":["builtins.str",{".class":"AnyType","missing_import_name":null,"source_any":null,"type_of_any":6}],"extra_attrs":null,"type_ref":"builtins.dict"}}},"__doc__":{".class":"SymbolTableNode","kind":"Gdef","node":{".class":"Var","flags":["is_ready"],"fullname":"assistant.modules.calendar.calendar_config.__doc__","name":"__doc__","type":"builtins.str"}},"__file__":{".class":"SymbolTableNode","kind":"Gdef","node":{".class":"Var","flags":["is_ready"],"fullname":"assistant.modules.calendar.calendar_config.__file__","name":"__file__","type":"builtins.str"}},"__name__":{".class":"SymbolTableNode","kind":"Gdef","node":{".class":"Var","flags":["is_ready"],"fullname":"assistant.modules.calendar.calendar_config.__name__","name":"__name__","type":"builtins.str"}},"__package__":{".class":"SymbolTableNode","kind":"Gdef","node":{".class":"Var","flags":["is_ready"],"fullname":"assistant.modules.calendar.calendar_config.__package__","name":"__package__","type":"builtins.str"}},"__spec__":{".class":"SymbolTableNode","kind":"Gdef","node":{".class":"Var","flags":["is_ready"],"fullname":"assistant.modules.calendar.calendar_config.__spec__","name":"__spec__","type":"importlib.machinery.ModuleSpec"}},"config_dir":{".class":"SymbolTableNode","kind":"Gdef","node":{".class":"Var","flags":["is_inferred","has_explicit_value"],"fullname":"assistant.modules.calendar.calendar_config.config_dir","name":"config_dir","type":"pathlib.Path"}},"create_engine":{".class":"SymbolTableNode","cross_ref":"sqlalchemy.engine.create.create_engine","kind":"Gdef"},"engine":{".class":"SymbolTableNode","kind":"Gdef","node":{".class":"Var","flags":["is_inferred","has_explicit_value"],"fullname":"assistant.modules.calendar.calendar_config.engine","name":"engine","type":"sqlalchemy.engine.base.Engine"}},"load_dotenv":{".class":"SymbolTableNode","cross_ref":"dotenv.main.load_dotenv","kind":"Gdef"},"os":{".class":"SymbolTableNode","cross_ref":"os","kind":"Gdef"}},"path":"assistant/modules/calendar/calendar_config.py"}