{"data_mtime":1763918258,"dep_lines":[37,40,41,44,45,51,52,70,71,84,94,3713,34,36,38,42,42,42,43,56,57,68,69,33,35,42,2,4,5,6,7,8,9,10,11,13,32,1,1,1,1,1,1,1,1,1,1,1,1,1,1,1,1,1,1,1,1,1,1,1,1,1,1,1,1,1,1,1,1,1,1,1,1,1,1,1,1,1,1,1,1,1,1,1,1,30,29],"dep_prios":[5,5,5,5,5,5,5,5,5,5,5,20,5,5,5,10,10,10,5,5,5,5,5,10,5,20,5,10,10,10,5,10,10,10,10,5,10,5,20,20,20,20,20,20,20,20,20,20,20,20,20,20,20,20,20,20,20,20,20,20,20,20,30,30,30,30,30,30,30,30,30,30,30,30,30,30,30,30,30,30,30,30,30,30,30,5,10],"dependencies":["torch.utils._sympy.functions","torch.utils._sympy.symbol","torch.utils._sympy.value_ranges","torch._inductor.runtime.benchmarking","torch._inductor.runtime.hints","torch._inductor.runtime.runtime_utils","torch._inductor.runtime.triton_heuristics","torch._inductor.codegen.block_analysis","torch._inductor.codegen.common","torch._inductor.codegen.simd","torch._inductor.codegen.triton_utils","torch._inductor.codegen.triton_split_scan","torch._dynamo.utils","torch.utils._ordered_set","torch.utils._triton","torch._inductor.config","torch._inductor.ir","torch._inductor.metrics","torch._inductor.codecache","torch._inductor.scheduler","torch._inductor.utils","torch._inductor.virtualized","torch._inductor.wrapper_benchmark","torch._logging","torch._prims_common","torch._inductor","__future__","collections","contextlib","dataclasses","functools","itertools","logging","os","textwrap","typing","torch","builtins","sys","altair.vegalite.v5.api","altair.vegalite.v5.schema","re","multiprocessing.reduction","torch.nn","html","altair.vegalite.v5.schema.core","traceback","warnings","operator","string","altair.vegalite.v5.schema.channels","math","enum","torch.distributed._functional_collectives","types","altair.vegalite.v5.schema.mixins","copy","pprint","inspect","altair.vegalite.v5.compiler","transformers.utils.logging","torch.distributed","_collections_abc","_typeshed","abc","importlib","importlib.machinery","torch._C","torch._C._VariableFunctions","torch._dynamo","torch._inductor.codegen.multi_kernel","torch._inductor.codegen.simd_kernel_features","torch._inductor.graph","torch._inductor.lowering","torch._inductor.ops_handler","torch._inductor.runtime","torch._inductor.sizevars","torch._logging._internal","torch.fx","torch.fx.interpreter","torch.utils","torch.utils._sympy","torch.utils._sympy.printers","torch.version","typing_extensions"],"hash":"5209c5fcf15e07288b97e98f1b72425ae9a8391a7fa587de984c8c42682df992","id":"torch._inductor.codegen.triton","ignore_all":true,"interface_hash":"cf5b8a579505381061330b2d6c8b257786b14d8fac7588448fd67376d435fbb3","mtime":1742057325,"options":{"allow_redefinition":false,"allow_untyped_globals":false,"always_false":[],"always_true":[],"bazel":false,"check_untyped_defs":true,"disable_bytearray_promotion":false,"disable_error_code":[],"disable_memoryview_promotion":false,"disabled_error_codes":[],"disallow_any_decorated":false,"disallow_any_explicit":false,"disallow_any_expr":false,"disallow_any_generics":false,"disallow_any_unimported":false,"disallow_incomplete_defs":false,"disallow_subclassing_any":false,"disallow_untyped_calls":false,"disallow_untyped_decorators":false,"disallow_untyped_defs":false,"enable_error_code":[],"enabled_error_codes":[],"extra_checks":false,"follow_imports":"normal","follow_imports_for_stubs":false,"ignore_errors":false,"ignore_missing_imports":true,"implicit_optional":false,"implicit_reexport":true,"local_partial_types":false,"mypyc":false,"old_type_inference":false,"platform":"darwin","plugins":[],"strict_concatenate":false,"strict_equality":false,"strict_optional":true,"warn_no_return":true,"warn_return_any":true,"warn_unreachable":false,"warn_unused_ignores":true},"path":"/Users/robertfreyne/.pyenv/versions/3.12.1/lib/python3.12/site-packages/torch/_inductor/codegen/triton.py","plugin_data":null,"size":149085,"suppressed":["sympy.printing.precedence","sympy"],"version_id":"1.11.2"}