{"data_mtime":1763918259,"dep_lines":[30,16,22,29,15,17,18,20,45,1,1,1,1,1,1,1,1,1,1,1,1,1,1,1,1,1,1,1,1,1,1,1,1,1,1,1,1,1,1,1,1,1,1,1,1,1,1,51,40,48,51],"dep_prios":[5,5,5,5,5,5,5,10,10,5,20,20,20,20,20,20,20,20,20,20,20,20,20,20,20,20,20,20,20,20,20,20,20,20,20,30,30,30,30,30,30,30,30,30,30,30,30,10,10,10,20],"dependencies":["transformers.utils.import_utils","collections.abc","transformers.image_utils","transformers.utils","collections","math","typing","numpy","torch","builtins","sys","itertools","altair.vegalite.v5.api","altair.vegalite.v5.schema","re","multiprocessing.reduction","torch.nn","html","altair.vegalite.v5.schema.core","os","traceback","warnings","operator","string","altair.vegalite.v5.schema.channels","enum","torch.distributed._functional_collectives","types","altair.vegalite.v5.schema.mixins","copy","pprint","inspect","altair.vegalite.v5.compiler","transformers.utils.logging","torch.distributed","abc","functools","huggingface_hub","huggingface_hub.utils","huggingface_hub.utils._runtime","importlib","importlib.machinery","numpy._typing","torch._C","torch._tensor","transformers.utils.generic","typing_extensions"],"hash":"88e55f70d49404d85b4cca3b0826bf9e29630eb0afb828d37f4347c1fb07986e","id":"transformers.image_transforms","ignore_all":true,"interface_hash":"537ad3729b824faf3929280b3e6b55c8d67850076895f0e6d46638593e8c3559","mtime":1761316315,"options":{"allow_redefinition":false,"allow_untyped_globals":false,"always_false":[],"always_true":[],"bazel":false,"check_untyped_defs":true,"disable_bytearray_promotion":false,"disable_error_code":[],"disable_memoryview_promotion":false,"disabled_error_codes":[],"disallow_any_decorated":false,"disallow_any_explicit":false,"disallow_any_expr":false,"disallow_any_generics":false,"disallow_any_unimported":false,"disallow_incomplete_defs":false,"disallow_subclassing_any":false,"disallow_untyped_calls":false,"disallow_untyped_decorators":false,"disallow_untyped_defs":false,"enable_error_code":[],"enabled_error_codes":[],"extra_checks":false,"follow_imports":"normal","follow_imports_for_stubs":false,"ignore_errors":false,"ignore_missing_imports":true,"implicit_optional":false,"implicit_reexport":true,"local_partial_types":false,"mypyc":false,"old_type_inference":false,"platform":"darwin","plugins":[],"strict_concatenate":false,"strict_equality":false,"strict_optional":true,"warn_no_return":true,"warn_return_any":true,"warn_unreachable":false,"warn_unused_ignores":true},"path":"/Users/robertfreyne/.pyenv/versions/3.12.1/lib/python3.12/site-packages/transformers/image_transforms.py","plugin_data":null,"size":41515,"suppressed":["jax.numpy","PIL","tensorflow","jax"],"version_id":"1.11.2"}