{"data_mtime":1763918257,"dep_lines":[31,17,18,29,31,1,1,1,1,1,1,1,1,1,1,1,1,1,1,1,1,1,1,1,1,1,1,1,1,1,1,1,1,1,1,1],"dep_prios":[10,5,10,5,20,5,20,20,20,20,20,20,20,20,20,20,20,20,20,20,20,20,20,20,20,20,20,20,20,20,20,20,20,30,30,30],"dependencies":["huggingface_hub.constants","logging","os","typing","huggingface_hub","builtins","sys","itertools","altair.vegalite.v5.api","altair.vegalite.v5.schema","re","html","altair.vegalite.v5.schema.core","traceback","warnings","string","altair.vegalite.v5.schema.channels","enum","types","altair.vegalite.v5.schema.mixins","copy","pprint","collections","inspect","altair.vegalite.v5.compiler","multiprocessing.reduction","torch.nn","operator","transformers.utils.logging","torch.distributed","math","torch.distributed._functional_collectives","torch","abc","importlib","importlib.machinery"],"hash":"37a35768271b3db65217e39ef936376679a4a667455724ce57c012a3ec955cb1","id":"huggingface_hub.utils.logging","ignore_all":true,"interface_hash":"95127b357a37e34fc9ef7b52dbc8780caa861edb7788a66b2832c24583b50ea6","mtime":1761316312,"options":{"allow_redefinition":false,"allow_untyped_globals":false,"always_false":[],"always_true":[],"bazel":false,"check_untyped_defs":true,"disable_bytearray_promotion":false,"disable_error_code":[],"disable_memoryview_promotion":false,"disabled_error_codes":[],"disallow_any_decorated":false,"disallow_any_explicit":false,"disallow_any_expr":false,"disallow_any_generics":false,"disallow_any_unimported":false,"disallow_incomplete_defs":false,"disallow_subclassing_any":false,"disallow_untyped_calls":false,"disallow_untyped_decorators":false,"disallow_untyped_defs":false,"enable_error_code":[],"enabled_error_codes":[],"extra_checks":false,"follow_imports":"normal","follow_imports_for_stubs":false,"ignore_errors":false,"ignore_missing_imports":true,"implicit_optional":false,"implicit_reexport":true,"local_partial_types":false,"mypyc":false,"old_type_inference":false,"platform":"darwin","plugins":[],"strict_concatenate":false,"strict_equality":false,"strict_optional":true,"warn_no_return":true,"warn_return_any":true,"warn_unreachable":false,"warn_unused_ignores":true},"path":"/Users/robertfreyne/.pyenv/versions/3.12.1/lib/python3.12/site-packages/huggingface_hub/utils/logging.py","plugin_data":null,"size":4916,"suppressed":[],"version_id":"1.11.2"}